{
  "id": "019d79df-e244-7ef1-9d72-067677031054",
  "content": "# git-lfs for weights\n\n## CLI\n\n```\npython -m benchmarks.upscale_bench.run [OPTIONS]\n\nOptions:\n  --clip PATH               Default: footage/raw/2025-11-01/DJI_20251101111428_0055_D_3s.MP4\n  --frames auto|N,N,N       Default: auto (heuristic-picked); override: \"30,180,300\"\n  --methods all|A,B,C       Default: all; e.g. \"bilinear,bicubic,joint_bilateral\"\n  --out-dir DIR             Default: working/upscale_bench/\n  --proxy-size N            Default: 1080 (matches production)\n  --regen-gold              Force gold recomputation, ignore cache\n  --gold-sanity-check       Run both native and tiled gold, report disagreement\n  --timing-runs N           Default: 10\n  --timing-warmup N         Default: 3\n  --verbose                 Log per-frame per-method progress\n```\n\nDefaults are chosen so `python -m benchmarks.upscale_bench.run` with zero args does the full benchmark on the canonical clip with all methods.\n",
  "source_version": "decisions/2026-04-10-delta-upscale-bench-design.md",
  "scope_id": "dorea",
  "workstream": "docs",
  "recorded_at": "2026-04-11T00:10:08.836207791Z",
  "valid_from": "2026-04-11T00:10:08.836207791Z",
  "valid_to": null,
  "superseded_by": null,
  "metadata": {
    "source_file": "decisions/2026-04-10-delta-upscale-bench-design.md",
    "language": null,
    "chunk_type": "heading_section",
    "start_line": 507,
    "end_line": 526,
    "content_role": "decision",
    "source_origin": "workspace"
  },
  "agent_id": null,
  "session_id": null,
  "entry_status": "Merged",
  "memory_type": "episodic",
  "confidence": null,
  "last_accessed": null,
  "access_count": 0,
  "tier": "hot",
  "tier_changed_at": null,
  "retention_score": null,
  "pin": null
}