{
  "id": "019d79da-752d-77c0-ad4d-d55a1bfa83aa",
  "content": " V2 model directory (used when --depth is omitted)\n    #[arg(long)]\n    pub depth_model: Option<PathBuf>,\n\n    /// Python executable (config: [models].python, built-in default: /opt/dorea-venv/bin/python)\n    #[arg(long)]\n    pub python: Option<PathBuf>,\n}\npub enum InputEncoding {\n    Srgb,\n    DlogM,\n}",
  "source_version": "crates/dorea-cli/src/calibrate.rs",
  "scope_id": "dorea",
  "workstream": "pipeline",
  "recorded_at": "2026-04-11T00:04:13.229481716Z",
  "valid_from": "2026-04-11T00:04:13.229481716Z",
  "valid_to": null,
  "superseded_by": null,
  "metadata": {
    "source_file": "crates/dorea-cli/src/calibrate.rs",
    "language": "rs",
    "chunk_type": "enum_item",
    "start_line": 165,
    "end_line": 168,
    "content_role": "code",
    "source_origin": "repo:dorea"
  },
  "agent_id": null,
  "session_id": null,
  "entry_status": "Merged",
  "memory_type": "episodic",
  "confidence": null,
  "last_accessed": null,
  "access_count": 0,
  "tier": "hot",
  "tier_changed_at": null,
  "retention_score": null,
  "pin": null
}