{
  "id": "019d79da-752d-77c0-ad4d-e763a50b2539",
  "content": "ne: bool,\n    ) -> Result<Vec<(String, Vec<u8>, usize, usize, Vec<f32>, usize, usize)>, InferenceError> {\n        if items.is_empty() {\n            return Ok(vec![]);\n        }\n\n        Python::with_gil(|py| {\n            let bridge = self.bridge.bind(py);\n\n            // Build Python list of (H, W, 3) numpy arrays\n            let py_list = pyo3::types::PyList::empty_bound(py);\n            for item in items {\n                let np_flat = numpy::PyArray1::from_slice_bound(py, &item.pixels);\n                let np_reshaped = np_flat\n                    .call_method1(\"reshape\", ((item.height, item.width, 3),))\n                    .map_err(|e| InferenceError::Ipc(format!(\"reshape for id={}: {e}\", item.id)))?;\n                py_list\n                    .append(np_reshaped)\n                    .map_err(|e| InferenceError::Ipc(format!(\"list append for id={}: {e}\", item.id)))?;\n            }\n\n            let raune_max = items[0].raune_max_size;\n            let depth_max = items[0].depth_max_size;\n\n            // Call bridge.run_raune_depth_batch_cpu(imgs, raune_max, depth_max, enable_maxine)\n            let result = bridge\n                .call_method1(\n                    \"run_raune_depth_batch_cpu\",\n                    (py_list, raune_max, depth_max, enable_maxine),\n                )\n                .map_err(|e| Self::map_python_error(py, e))?;\n\n            // Result is a Python list of (enhanced_np, depth_np) tuples\n            let result_list = result\n                .downcast::<pyo3::types::PyList>()\n                .map_err(|e| InferenceError::Ipc(format!(\n                    \"run_raune_depth_batch_cpu result not a list: {e}\"\n                )))?;\n\n            let mut out = Vec::with_capacity(items.len());\n            for (i, item) in items.iter().enumerate() {\n                let pair = result_list\n                    .get_item(i)\n                    .map_err(|e| InferenceError::Ipc(format!(\"get result[{i}]: {e}\")))?;\n\n                let pair_tuple = pair\n                    .downcast::<pyo3::types::PyTuple>()\n                    .map_err(|e| InferenceError::Ipc(format!(\"result[{i}] not a tuple: {e}\")))?;\n\n                // Enhanced RGB u8 array (H, W, 3)\n                let enhanced_arr = pair_tuple.get_item(0)",
  "source_version": "crates/dorea-video/src/inference/pyo3_backend.rs",
  "scope_id": "dorea",
  "workstream": "pipeline",
  "recorded_at": "2026-04-11T00:04:13.229703606Z",
  "valid_from": "2026-04-11T00:04:13.229703606Z",
  "valid_to": null,
  "superseded_by": null,
  "metadata": {
    "source_file": "crates/dorea-video/src/inference/pyo3_backend.rs",
    "language": "rs",
    "chunk_type": "impl_item",
    "start_line": 443,
    "end_line": 485,
    "content_role": "code",
    "source_origin": "repo:dorea"
  },
  "agent_id": null,
  "session_id": null,
  "entry_status": "Merged",
  "memory_type": "episodic",
  "confidence": null,
  "last_accessed": null,
  "access_count": 0,
  "tier": "hot",
  "tier_changed_at": null,
  "retention_score": null,
  "pin": null
}