{
  "id": "019d79da-752d-77c0-ad4d-f7a2ebed81a0",
  "content": "pub fn linear_to_ilog(x: f32) -> f32 {\n    let x = x as f64;\n    let encoded = if x >= LIN_CUT {\n        A * ((x + B) / 0.19).log10() + D\n    } else {\n        x * LIN_SLOPE + LIN_OFFSET\n    };\n    encoded.clamp(0.0, 1.0) as f32\n}\nimpl TransferFunction for ILog {\n    fn to_linear(&self, encoded: f32) -> f32 {\n        ilog_to_linear(encoded)\n    }\n\n    fn from_linear(&self, linear: f32) -> f32 {\n        linear_to_ilog(linear)\n    }\n\n    fn shoulder(&self) -> f32 {\n        0.88\n    }\n\n    fn name(&self) -> &str {\n        \"I-Log\"\n    }\n}",
  "source_version": "crates/dorea-color/src/ilog.rs",
  "scope_id": "dorea",
  "workstream": "pipeline",
  "recorded_at": "2026-04-11T00:04:13.229916528Z",
  "valid_from": "2026-04-11T00:04:13.229916528Z",
  "valid_to": null,
  "superseded_by": null,
  "metadata": {
    "source_file": "crates/dorea-color/src/ilog.rs",
    "language": "rs",
    "chunk_type": "impl_item",
    "start_line": 50,
    "end_line": 66,
    "content_role": "code",
    "source_origin": "repo:dorea"
  },
  "agent_id": null,
  "session_id": null,
  "entry_status": "Merged",
  "memory_type": "episodic",
  "confidence": null,
  "last_accessed": null,
  "access_count": 0,
  "tier": "hot",
  "tier_changed_at": null,
  "retention_score": null,
  "pin": null
}