{
  "id": "019d6b26-090a-7361-9475-dc262479f95b",
  "content": "\");\n        return Err(InferenceError::ServerError(msg.to_string()));\n    }\n    if v[\"type\"].as_str() != Some(\"enhance_result\") {\n        return Err(InferenceError::Ipc(format!(\n            \"unexpected response type for enhance: {resp}\"\n        )));\n    }\n\n    let w = v[\"width\"].as_u64().unwrap_or(0) as usize;\n    let h = v[\"height\"].as_u64().unwrap_or(0) as usize;\n\n    if w != expected_w || h != expected_h {\n        return Err(InferenceError::Ipc(format!(\n            \"enhance dimension mismatch: expected {expected_w}x{expected_h}, got {w}x{h}\"\n        )));\n    }\n\n    let b64_out = v[\"image_b64\"]\n        .as_str()\n        .ok_or_else(|| InferenceError::Ipc(\"missing image_b64\".to_string()))?;\n\n    let raw = B64\n        .decode(b64_out)\n        .map_err(|e| InferenceError::Ipc(format!(\"base64 decode: {e}\")))?;\n\n    if raw.len() != w * h * 3 {\n        return Err(InferenceError::Ipc(format!(\n            \"enhance buffer size mismatch: got {}, expected {}\",\n            raw.len(),\n            w * h * 3,\n        )));\n    }\n\n    Ok((raw, w, h))\n}\n```\n\n- [ ] **Step 4: Run test to verify it passes**\n\n```bash\ncd /workspaces/dorea-workspace/repos/dorea\ncargo test -p dorea-video enhance_ 2>&1 | tail -20\n```\n\nExpected: both `enhance_parses_valid_response` and `enhance_rejects_dimension_mismatch` PASS.\n\n- [ ] **Step 5: Add `enhance()` method to `InferenceServer`**\n\nAdd to the `impl InferenceServer` block, following the pattern of `run_depth()`:\n\n```rust\n    /// Send a graded RGB u8 frame for Maxine enhancement.\n    /// Returns enhanced RGB u8 at the same resolution as input.\n    pub fn enhance(\n        &mut self,",
  "source_version": "plans/2026-04-03-maxine-enhancement-impl.md",
  "scope_id": "dorea",
  "workstream": "docs",
  "recorded_at": "2026-04-08T03:32:28.042323779Z",
  "valid_from": "2026-04-08T03:32:28.042323779Z",
  "valid_to": null,
  "superseded_by": null,
  "metadata": {
    "source_file": "plans/2026-04-03-maxine-enhancement-impl.md",
    "language": null,
    "chunk_type": "heading_section",
    "start_line": 605,
    "end_line": 651,
    "content_role": "plan",
    "source_origin": "workspace"
  },
  "agent_id": null,
  "session_id": null,
  "entry_status": "Merged",
  "memory_type": "episodic",
  "confidence": null,
  "last_accessed": null,
  "access_count": 0,
  "tier": "hot",
  "tier_changed_at": null,
  "retention_score": null,
  "pin": null
}